spst/__init__.py
spst/core.py
spst-0.1.0.dist-info/LICENSE
spst-0.1.0.dist-info/METADATA
spst-0.1.0.dist-info/WHEEL
spst-0.1.0.dist-info/entry_points.txt
spst-0.1.0.dist-info/top_level.txt
spst-0.1.0.dist-info/RECORD
