Metadata-Version: 2.1
Name: spst
Version: 0.1.0
Summary: A package that prints Python code
Author: joint-suresh
Author-email: jointsuresh@outlook.com
Classifier: Programming Language :: Python :: 3
Classifier: License :: OSI Approved :: MIT License
Classifier: Operating System :: OS Independent
License-File: LICENSE
